saudi_regions/__init__.py
saudi_regions/data_loader.py
saudi_regions/data_models.py
saudi_regions/saudi_regions.py
saudi_regions_widget_py-2.0.0.dist-info/licenses/LICENSE
saudi_regions_widget_py-2.0.0.dist-info/METADATA
saudi_regions_widget_py-2.0.0.dist-info/WHEEL
saudi_regions_widget_py-2.0.0.dist-info/top_level.txt
saudi_regions_widget_py-2.0.0.dist-info/RECORD
