Metadata-Version: 2.4
Name: saudi-regions-widget-py
Version: 2.0.0
Summary: A Python library for Saudi Arabia regions, cities, and districts data.
Home-page: https://github.com/YounisDany/saudi-regions-widget-py
Author: Manus AI (Original by Younis Dany)
Author-email: support@manus.im
Classifier: Programming Language :: Python :: 3
Classifier: License :: OSI Approved :: MIT License
Classifier: Operating System :: OS Independent
Classifier: Development Status :: 4 - Beta
Classifier: Intended Audience :: Developers
Classifier: Topic :: Software Development :: Libraries :: Python Modules
Requires-Python: >=3.7
License-File: LICENSE
Requires-Dist: requests
Dynamic: author
Dynamic: author-email
Dynamic: classifier
Dynamic: description
Dynamic: description-content-type
Dynamic: home-page
Dynamic: license-file
Dynamic: requires-dist
Dynamic: requires-python
Dynamic: summary
